<manifest alg="2" build="2018.1.0.386" opt="false" iceEnabled="true" iceMarkupVersion="2" iceEnabledOptions="link,responsive,cachebuster,textStyling" exportTarget="other" domain="kexkeli.cn" resolutions="1x" timestamp="1586480859078">
  <folder name="css">
    <file name="site_global.css" crc="229390053"/>
    <file name="index.css" crc="232518531" ref="index"/>
  </folder>
  <folder name="fonts">
    <file name="oswald-bold.woff" crc="474070346"/>
    <file name="oswald-bold.eot" crc="3795542740"/>
  </folder>
  <folder name="assets">
    <file name="4-2.png" crc="4169017331" seo="true" mt="1586201918000"/>
    <file name="4-3.png" crc="20643916" seo="true" mt="1586201911000"/>
    <file name="4-4.png" crc="3772417167" seo="true" mt="1586201924000"/>
  </folder>
  <folder name="scripts">
    <file name="jquery-1.8.3.min.js" crc="209076791" ref="index"/>
    <file name="museutils.js" crc="340535759" ref="index"/>
    <file name="whatinput.js" crc="86476730" ref="index"/>
    <file name="museconfig.js" crc="4286661555" ref="index"/>
    <file name="require.js" crc="7928878" ref="index"/>
  </folder>
  <folder name="images">
    <file name="blank.gif" crc="4208392903" ref="index"/>
    <file name="1.jpg" crc="4156310770" seo="true" ref="index">
      <caption webpage="index" alt=""/>
    </file>
    <file name="2.png" crc="4135540732" seo="true" ref="index">
      <caption webpage="index" alt=""/>
    </file>
    <file name="3.png" crc="426675702" seo="true" ref="index">
      <caption webpage="index" alt=""/>
    </file>
    <file name="4.jpg" crc="4120607807" seo="true" ref="index">
      <caption webpage="index" alt=""/>
    </file>
    <file name="4-1.png" crc="69766589" seo="true" ref="index">
      <caption webpage="index" alt=""/>
    </file>
    <file name="5-1.jpg" crc="351482925" seo="true" ref="index">
      <caption webpage="index" alt=""/>
    </file>
    <file name="5-2.jpg" crc="118674457" seo="true" ref="index">
      <caption webpage="index" alt=""/>
    </file>
    <file name="5-3.jpg" crc="4055830972" seo="true" ref="index">
      <caption webpage="index" alt=""/>
    </file>
    <file name="5-4.jpg" crc="525044595" seo="true" ref="index">
      <caption webpage="index" alt=""/>
    </file>
    <file name="5-5.jpg" crc="451509946" seo="true" ref="index">
      <caption webpage="index" alt=""/>
    </file>
    <file name="6.jpg" crc="483962625" seo="true" ref="index">
      <caption webpage="index" alt=""/>
    </file>
    <file name="7-8.png" crc="289193691" seo="true" ref="index">
      <caption webpage="index" alt=""/>
    </file>
    <file name="7-9.png" crc="3816560647" seo="true" ref="index">
      <caption webpage="index" alt=""/>
    </file>
    <file name="7-10.png" crc="238200235" seo="true" ref="index">
      <caption webpage="index" alt=""/>
    </file>
    <file name="7-11.png" crc="3955669989" seo="true" ref="index">
      <caption webpage="index" alt=""/>
    </file>
    <file name="7-12.png" crc="3898279571" seo="true" ref="index">
      <caption webpage="index" alt=""/>
    </file>
    <file name="7-1.jpg" crc="515513551" seo="true" ref="index">
      <caption webpage="index" alt=""/>
    </file>
    <file name="7-2.jpg" crc="3800227668" seo="true" ref="index">
      <caption webpage="index" alt=""/>
    </file>
    <file name="7-3.jpg" crc="211036764" seo="true" ref="index">
      <caption webpage="index" alt=""/>
    </file>
    <file name="7-4.jpg" crc="4256756953" seo="true" ref="index">
      <caption webpage="index" alt=""/>
    </file>
    <file name="7-5.jpg" crc="3836575663" seo="true" ref="index">
      <caption webpage="index" alt=""/>
    </file>
    <file name="7-6.jpg" crc="220879453" seo="true" ref="index">
      <caption webpage="index" alt=""/>
    </file>
    <file name="5.png" crc="107939158" seo="true" ref="index">
      <caption webpage="index" alt=""/>
    </file>
    <file name="7.png" crc="3760261290" seo="true" ref="index">
      <caption webpage="index" alt=""/>
    </file>
    <file name="9.jpg" crc="221264165" seo="true" ref="index">
      <caption webpage="index" alt=""/>
    </file>
    <file name="10-1.jpg" crc="305882907" seo="true" ref="index">
      <caption webpage="index" alt=""/>
    </file>
    <file name="10-2-crop-u5412.jpg" crc="18480156" seo="true" ref="index">
      <caption webpage="index" alt=""/>
    </file>
    <file name="10-3.jpg" crc="4095303573" seo="true" ref="index">
      <caption webpage="index" alt=""/>
    </file>
    <file name="10-4.png" crc="4202914906" seo="true" ref="index">
      <caption webpage="index" alt=""/>
    </file>
    <file name="10-5.png" crc="536366974" seo="true" ref="index">
      <caption webpage="index" alt=""/>
    </file>
    <file name="10.png" crc="62172629" seo="true" ref="index">
      <caption webpage="index" alt=""/>
    </file>
    <file name="11.png" crc="29286286" seo="true" ref="index">
      <caption webpage="index" alt=""/>
    </file>
  </folder>
  <file name="index.html" crc="29465585" mt="1586480811002" redirect="true"/>
</manifest>